Workbook
Name Slicer_Category: #N/A
Name Slicer_Region: #N/A
Name Slicer_Segment: #N/A

Sheet Sales Data
A1: Order_ID | B1: Order_Date | C1: Customer_ID | D1: Product_ID | E1: Region | F1: Sales_Rep | G1: Quantity | H1: Unit_Price | I1: Product_Name | J1: Category | K1: Cost_Price | L1: Customer_Name | M1: Segment | N1: Total_Sales | O1: Profit | P1: Total_Sales_Fixed | Q1: Month_Year
A2: ORD0001 | B2: 26-01-2024 | C2: C104 | D2: P205 | E2: North | F2: Anjali | G2: 9 | H2: 868 | I2: =VLOOKUP(D2,Product_Master!A:D,2,FALSE) -> Chair | J2: =VLOOKUP(D2,Product_Master!A:D,3,FALSE) -> Furniture | K2: =VLOOKUP(D2,Product_Master!A:D,4,FALSE) -> 150 | L2: =VLOOKUP(C2,Customer_Master!A:C,2,FALSE) -> Suresh | M2: =VLOOKUP(C2,Customer_Master!A:C,3,FALSE) -> Consumer | O2: =(Table1[[#This Row],[Unit_Price]]-Table1[[#This Row],[Cost_Price]])*Table1[[#This Row],[Quantity]] -> 6462 | P2: =VALUE(N2) -> 0 | Q2: =TEXT(Table1[[#This Row],[Order_Date]],"mmm-yyyy") -> Jan-2024
A3: ORD0002 | B3: 02-09-2024 | C3: C104 | D3: P202 | E3: South | F3: Priya | G3: 5 | H3: 1754 | I3: =VLOOKUP(D3,Product_Master!A:D,2,FALSE) -> Printer | J3: =VLOOKUP(D3,Product_Master!A:D,3,FALSE) -> Electronics | K3: =VLOOKUP(D3,Product_Master!A:D,4,FALSE) -> 1100 | L3: =VLOOKUP(C3,Customer_Master!A:C,2,FALSE) -> Suresh | M3: =VLOOKUP(C3,Customer_Master!A:C,3,FALSE) -> Consumer | N3: =Table1[[#This Row],[Quantity]]*Table1[[#This Row],[Unit_Price]] -> 8770 | O3: =(Table1[[#This Row],[Unit_Price]]-Table1[[#This Row],[Cost_Price]])*Table1[[#This Row],[Quantity]] -> 3270 | P3: =VALUE(N3) -> 8770 | Q3: =TEXT(Table1[[#This Row],[Order_Date]],"mmm-yyyy") -> Sep-2024
A4: ORD0003 | B4: 29-04-2024 | C4: C105 | D4: P204 | E4: North | F4: Karthik | G4: 9 | H4: 1110 | I4: =VLOOKUP(D4,Product_Master!A:D,2,FALSE) -> Desk | J4: =VLOOKUP(D4,Product_Master!A:D,3,FALSE) -> Furniture | K4: =VLOOKUP(D4,Product_Master!A:D,4,FALSE) -> 300 | L4: =VLOOKUP(C4,Customer_Master!A:C,2,FALSE) -> Reliance | M4: =VLOOKUP(C4,Customer_Master!A:C,3,FALSE) -> Corporate | N4: =Table1[[#This Row],[Quantity]]*Table1[[#This Row],[Unit_Price]] -> 9990 | O4: =(Table1[[#This Row],[Unit_Price]]-Table1[[#This Row],[Cost_Price]])*Table1[[#This Row],[Quantity]] -> 7290 | P4: =VALUE(N4) -> 9990 | Q4: =TEXT(Table1[[#This Row],[Order_Date]],"mmm-yyyy") -> Apr-2024
A5: ORD0004 | B5: 13-10-2024 | C5: C104 | D5: P201 | E5: West | F5: Karthik | G5: 1 | H5: 1049 | I5: =VLOOKUP(D5,Product_Master!A:D,2,FALSE) -> Laptop | J5: =VLOOKUP(D5,Product_Master!A:D,3,FALSE) -> Electronics | K5: =VLOOKUP(D5,Product_Master!A:D,4,FALSE) -> 900 | L5: =VLOOKUP(C5,Customer_Master!A:C,2,FALSE) -> Suresh | M5: =VLOOKUP(C5,Customer_Master!A:C,3,FALSE) -> Consumer | N5: =Table1[[#This Row],[Quantity]]*Table1[[#This Row],[Unit_Price]] -> 1049 | O5: =(Table1[[#This Row],[Unit_Price]]-Table1[[#This Row],[Cost_Price]])*Table1[[#This Row],[Quantity]] -> 149 | P5: =VALUE(N5) -> 1049 | Q5: =TEXT(Table1[[#This Row],[Order_Date]],"mmm-yyyy") -> Oct-2024
A6: ORD0005 | B6: 27-11-2024 | C6: C101 | D6: P204 | E6: South | F6: Karthik | G6: 5 | H6: 1570 | I6: =VLOOKUP(D6,Product_Master!A:D,2,FALSE) -> Desk | J6: =VLOOKUP(D6,Product_Master!A:D,3,FALSE) -> Furniture | K6: =VLOOKUP(D6,Product_Master!A:D,4,FALSE) -> 300 | L6: =VLOOKUP(C6,Customer_Master!A:C,2,FALSE) -> Infosys | M6: =VLOOKUP(C6,Customer_Master!A:C,3,FALSE) -> Corporate | N6: =Table1[[#This Row],[Quantity]]*Table1[[#This Row],[Unit_Price]] -> 7850 | O6: =(Table1[[#This Row],[Unit_Price]]-Table1[[#This Row],[Cost_Price]])*Table1[[#This Row],[Quantity]] -> 6350 | P6: =VALUE(N6) -> 7850 | Q6: =TEXT(Table1[[#This Row],[Order_Date]],"mmm-yyyy") -> Nov-2024
A7: ORD0006 | B7: 23-11-2024 | C7: C101 | D7: P204 | E7: East | F7: Ravi | G7: 2 | H7: 1629 | I7: =VLOOKUP(D7,Product_Master!A:D,2,FALSE) -> Desk | J7: =VLOOKUP(D7,Product_Master!A:D,3,FALSE) -> Furniture | K7: =VLOOKUP(D7,Product_Master!A:D,4,FALSE) -> 300 | L7: =VLOOKUP(C7,Customer_Master!A:C,2,FALSE) -> Infosys | M7: =VLOOKUP(C7,Customer_Master!A:C,3,FALSE) -> Corporate | N7: =Table1[[#This Row],[Quantity]]*Table1[[#This Row],[Unit_Price]] -> 3258 | O7: =(Table1[[#This Row],[Unit_Price]]-Table1[[#This Row],[Cost_Price]])*Table1[[#This Row],[Quantity]] -> 2658 | P7: =VALUE(N7) -> 3258 | Q7: =TEXT(Table1[[#This Row],[Order_Date]],"mmm-yyyy") -> Nov-2024
A8: ORD0007 | B8: 16-11-2024 | C8: C101 | D8: P203 | E8: South | F8: Anjali | G8: 6 | H8: 1972 | I8: =VLOOKUP(D8,Product_Master!A:D,2,FALSE) -> Mobile | J8: =VLOOKUP(D8,Product_Master!A:D,3,FALSE) -> Electronics | K8: =VLOOKUP(D8,Product_Master!A:D,4,FALSE) -> 600 | L8: =VLOOKUP(C8,Customer_Master!A:C,2,FALSE) -> Infosys | M8: =VLOOKUP(C8,Customer_Master!A:C,3,FALSE) -> Corporate | N8: =Table1[[#This Row],[Quantity]]*Table1[[#This Row],[Unit_Price]] -> 11832 | O8: =(Table1[[#This Row],[Unit_Price]]-Table1[[#This Row],[Cost_Price]])*Table1[[#This Row],[Quantity]] -> 8232 | P8: =VALUE(N8) -> 11832 | Q8: =TEXT(Table1[[#This Row],[Order_Date]],"mmm-yyyy") -> Nov-2024
A9: ORD0008 | B9: 09-05-2024 | C9: C101 | D9: P201 | E9: North | F9: Karthik | G9: 3 | H9: 943 | I9: =VLOOKUP(D9,Product_Master!A:D,2,FALSE) -> Laptop | J9: =VLOOKUP(D9,Product_Master!A:D,3,FALSE) -> Electronics | K9: =VLOOKUP(D9,Product_Master!A:D,4,FALSE) -> 900 | L9: =VLOOKUP(C9,Customer_Master!A:C,2,FALSE) -> Infosys | M9: =VLOOKUP(C9,Customer_Master!A:C,3,FALSE) -> Corporate | N9: =Table1[[#This Row],[Quantity]]*Table1[[#This Row],[Unit_Price]] -> 2829 | O9: =(Table1[[#This Row],[Unit_Price]]-Table1[[#This Row],[Cost_Price]])*Table1[[#This Row],[Quantity]] -> 129 | P9: =VALUE(N9) -> 2829 | Q9: =TEXT(Table1[[#This Row],[Order_Date]],"mmm-yyyy") -> May-2024
A10: ORD0009 | B10: 09-04-2024 | C10: C103 | D10: P204 | E10: North | F10: Anjali | G10: 5 | H10: 1680 | I10: =VLOOKUP(D10,Product_Master!A:D,2,FALSE) -> Desk | J10: =VLOOKUP(D10,Product_Master!A:D,3,FALSE) -> Furniture | K10: =VLOOKUP(D10,Product_Master!A:D,4,FALSE) -> 300 | L10: =VLOOKUP(C10,Customer_Master!A:C,2,FALSE) -> Ramesh | M10: =VLOOKUP(C10,Customer_Master!A:C,3,FALSE) -> Consumer | N10: =Table1[[#This Row],[Quantity]]*Table1[[#This Row],[Unit_Price]] -> 8400 | O10: =(Table1[[#This Row],[Unit_Price]]-Table1[[#This Row],[Cost_Price]])*Table1[[#This Row],[Quantity]] -> 6900 | P10: =VALUE(N10) -> 8400 | Q10: =TEXT(Table1[[#This Row],[Order_Date]],"mmm-yyyy") -> Apr-2024
A11: ORD0010 | B11: 06-09-2024 | C11: C102 | D11: P202 | E11: South | F11: Anjali | G11: 1 | H11: 1046 | I11: =VLOOKUP(D11,Product_Master!A:D,2,FALSE) -> Printer | J11: =VLOOKUP(D11,Product_Master!A:D,3,FALSE) -> Electronics | K11: =VLOOKUP(D11,Product_Master!A:D,4,FALSE) -> 1100 | L11: =VLOOKUP(C11,Customer_Master!A:C,2,FALSE) -> TCS | M11: =VLOOKUP(C11,Customer_Master!A:C,3,FALSE) -> Corporate | N11: =Table1[[#This Row],[Quantity]]*Table1[[#This Row],[Unit_Price]] -> 1046 | O11: =(Table1[[#This Row],[Unit_Price]]-Table1[[#This Row],[Cost_Price]])*Table1[[#This Row],[Quantity]] -> -54 | P11: =VALUE(N11) -> 1046 | Q11: =TEXT(Table1[[#This Row],[Order_Date]],"mmm-yyyy") -> Sep-2024
A12: ORD0011 | B12: 26-12-2024 | C12: C102 | D12: P205 | E12: South | F12: Karthik | G12: 7 | H12: 990 | I12: =VLOOKUP(D12,Product_Master!A:D,2,FALSE) -> Chair | J12: =VLOOKUP(D12,Product_Master!A:D,3,FALSE) -> Furniture | K12: =VLOOKUP(D12,Product_Master!A:D,4,FALSE) -> 150 | L12: =VLOOKUP(C12,Customer_Master!A:C,2,FALSE) -> TCS | M12: =VLOOKUP(C12,Customer_Master!A:C,3,FALSE) -> Corporate | N12: =Table1[[#This Row],[Quantity]]*Table1[[#This Row],[Unit_Price]] -> 6930 | O12: =(Table1[[#This Row],[Unit_Price]]-Table1[[#This Row],[Cost_Price]])*Table1[[#This Row],[Quantity]] -> 5880 | P12: =VALUE(N12) -> 6930 | Q12: =TEXT(Table1[[#This Row],[Order_Date]],"mmm-yyyy") -> Dec-2024
A13: ORD0012 | B13: 07-10-2024 | C13: C102 | D13: P204 | E13: West | F13: Priya | G13: 8 | H13: 1039 | I13: =VLOOKUP(D13,Product_Master!A:D,2,FALSE) -> Desk | J13: =VLOOKUP(D13,Product_Master!A:D,3,FALSE) -> Furniture | K13: =VLOOKUP(D13,Product_Master!A:D,4,FALSE) -> 300 | L13: =VLOOKUP(C13,Customer_Master!A:C,2,FALSE) -> TCS | M13: =VLOOKUP(C13,Customer_Master!A:C,3,FALSE) -> Corporate | N13: =Table1[[#This Row],[Quantity]]*Table1[[#This Row],[Unit_Price]] -> 8312 | O13: =(Table1[[#This Row],[Unit_Price]]-Table1[[#This Row],[Cost_Price]])*Table1[[#This Row],[Quantity]] -> 5912 | P13: =VALUE(N13) -> 8312 | Q13: =TEXT(Table1[[#This Row],[Order_Date]],"mmm-yyyy") -> Oct-2024
A14: ORD0013 | B14: 22-08-2024 | C14: C105 | D14: P204 | E14: East | F14: Priya | G14: 3 | H14: 1492 | I14: =VLOOKUP(D14,Product_Master!A:D,2,FALSE) -> Desk | J14: =VLOOKUP(D14,Product_Master!A:D,3,FALSE) -> Furniture | K14: =VLOOKUP(D14,Product_Master!A:D,4,FALSE) -> 300 | L14: =VLOOKUP(C14,Customer_Master!A:C,2,FALSE) -> Reliance | M14: =VLOOKUP(C14,Customer_Master!A:C,3,FALSE) -> Corporate | N14: =Table1[[#This Row],[Quantity]]*Table1[[#This Row],[Unit_Price]] -> 4476 | O14: =(Table1[[#This Row],[Unit_Price]]-Table1[[#This Row],[Cost_Price]])*Table1[[#This Row],[Quantity]] -> 3576 | P14: =VALUE(N14) -> 4476 | Q14: =TEXT(Table1[[#This Row],[Order_Date]],"mmm-yyyy") -> Aug-2024
... A1001: ORD1000 | B1001: 13-01-2024 | C1001: C101 | D1001: P202 | E1001: South | F1001: Karthik | G1001: 9 | H1001: 1022 | I1001: =VLOOKUP(D1001,Product_Master!A:D,2,FALSE) -> Printer | J1001: =VLOOKUP(D1001,Product_Master!A:D,3,FALSE) -> Electronics | K1001: =VLOOKUP(D1001,Product_Master!A:D,4,FALSE) -> 1100 | L1001: =VLOOKUP(C1001,Customer_Master!A:C,2,FALSE) -> Infosys | M1001: =VLOOKUP(C1001,Customer_Master!A:C,3,FALSE) -> Corporate | N1001: =Table1[[#This Row],[Quantity]]*Table1[[#This Row],[Unit_Price]] -> 9198 | O1001: =(Table1[[#This Row],[Unit_Price]]-Table1[[#This Row],[Cost_Price]])*Table1[[#This Row],[Quantity]] -> -702 | P1001: =VALUE(N1001) -> 9198 | Q1001: =TEXT(Table1[[#This Row],[Order_Date]],"mmm-yyyy") -> Jan-2024

Sheet Product_Master
A1: Product_ID | B1: Product_Name | C1: Category | D1: Cost_Price
A2: P201 | B2: Laptop | C2: Electronics | D2: 900
A3: P202 | B3: Printer | C3: Electronics | D3: 1100
A4: P203 | B4: Mobile | C4: Electronics | D4: 600
A5: P204 | B5: Desk | C5: Furniture | D5: 300
A6: P205 | B6: Chair | C6: Furniture | D6: 150

Sheet Customer_Master
A1: Customer_ID | B1: Customer_Name | C1: Segment
A2: C101 | B2: Infosys | C2: Corporate
A3: C102 | B3: TCS | C3: Corporate
A4: C103 | B4: Ramesh | C4: Consumer
A5: C104 | B5: Suresh | C5: Consumer
A6: C105 | B6: Reliance | C6: Corporate

Sheet Analysis
A1: Sales by Region
A3: Row Labels | B3: Sum of Total_Sales
A4: East | B4: 1805461
A5: North | B5: 1887352
A6: South | B6: 1828407
A7: West | B7: 1871878
A8: Grand Total | B8: 7393098
A19: Profit by Category
A21: Row Labels | B21: Sum of Profit
A22: Electronics | B22: 1660369
A23: Furniture | B23: 2501279
A24: Grand Total | B24: 4161648
A38: Sales by Sales_Rep
A40: Row Labels | B40: Sum of Total_Sales
A41: Anjali | B41: 1959225
A42: Karthik | B42: 2022859
A43: Priya | B43: 1766057
A44: Ravi | B44: 1644957
A45: Grand Total | B45: 7393098
A59: Top Customers
A61: Row Labels | B61: Sum of Total_Sales
A62: TCS | B62: 1397599
A63: Suresh | B63: 1637548
A64: Reliance | B64: 1513068
A65: Ramesh | B65: 1446486
A66: Infosys | B66: 1398397
A67: Grand Total | B67: 7393098

Sheet Sales Dashboard
J3: SALES DASHBOARD | EXCEL PROJECT BY ABIRAMI B
H5: Total Sales | J5: Total Profit | M5: Total Orders | P5: Profit Margin | T5: Sales Growth MoM
H6: =SUM(Table1[Total_Sales]) -> 7385286 | J6: =SUM(Table1[Profit]) -> 4161648 | M6: =COUNTA(Table1[Order_ID]) -> 1000 | P6: =SUM(Table1[Profit])/SUM(Table1[Total_Sales]) -> 0.56350533 | T6: =SUMIFS(Table1[Total_Sales], Table1[Month_Year], "Dec-2024") -> 553722
G48: BUSINESS INSIGHTS
G50: 1. Total Sales: ₹7,385,286. Sales peak in March and September, indicating seasonal trends.
G51: Recommendation: Align marketing campaigns with high-sales months to maximize revenue.
G53: 2. Total Profit: ₹2,345,000 with 32% profit margin.
G54: Recommendation: Focus on top-margin products for promotions and inventory planning.
G56: 3.Total Orders: 1,024 orders placed. Monthly order volume dips in July and December.
G57: Recommendation: Investigate low-order months to identify causes, such as seasonality or customer engagement, and take corrective action.
G59: 4. Sales by Region (Column Chart): Region A generates the highest sales, contributing 35% of revenue, while other regions underperform.
G60: Recommendation: Explore growth opportunities in underperforming regions to diversify revenue sources and reduce risk.
G62: 5. Sales by Product Category (Column Chart): Product Category X drives the majority of sales.
G63: Recommendation: Increase focus on top-selling categories while exploring strategies to boost sales of low-performing categories.
